chemeleon_dng/__init__.py
chemeleon_dng/base_module.py
chemeleon_dng/cspnet.py
chemeleon_dng/datamodule.py
chemeleon_dng/download_util.py
chemeleon_dng/sample.py
chemeleon_dng/scatter.py
chemeleon_dng/schema.py
chemeleon_dng/script_util.py
chemeleon_dng/dataset/__init__.py
chemeleon_dng/dataset/dataset_util.py
chemeleon_dng/dataset/mp_dataset.py
chemeleon_dng/dataset/num_atom_distributions.py
chemeleon_dng/diffusion/__init__.py
chemeleon_dng/diffusion/diffusion_module.py
chemeleon_dng/diffusion/diffusion_scheduler.py
chemeleon_dng/diffusion/models/__init__.py
chemeleon_dng/diffusion/models/base.py
chemeleon_dng/diffusion/models/d3pm.py
chemeleon_dng/diffusion/models/ddpm.py
chemeleon_dng/diffusion/models/dsm.py
chemeleon_dng-0.1.5.dist-info/licenses/LICENSE
chemeleon_dng-0.1.5.dist-info/METADATA
chemeleon_dng-0.1.5.dist-info/WHEEL
chemeleon_dng-0.1.5.dist-info/entry_points.txt
chemeleon_dng-0.1.5.dist-info/top_level.txt
chemeleon_dng-0.1.5.dist-info/RECORD
