Metadata-Version: 2.4
Name: chemeleon-dng
Version: 0.1.5
Summary: Chemeleon framework for De Novo Generation (DNG) and Crystal Structure Prediction (CSP) tasks
Author-email: Hyunsoo Park <hspark1212@gmail.com>
Maintainer-email: Hyunsoo Park <hspark1212@gmail.com>
License-Expression: MIT
Project-URL: Homepage, https://github.com/hspark1212/chemeleon-dng
Project-URL: Repository, https://github.com/hspark1212/chemeleon-dng
Project-URL: Issues, https://github.com/hspark1212/chemeleon-dng/issues
Project-URL: Documentation, https://github.com/hspark1212/chemeleon-dng#readme
Keywords: crystal structure,materials science,generative AI,diffusion models,crystal structure prediction,de novo generation
Classifier: Development Status :: 4 - Beta
Classifier: Intended Audience :: Science/Research
Classifier: Programming Language :: Python :: 3
Classifier: Programming Language :: Python :: 3.11
Classifier: Programming Language :: Python :: 3.12
Classifier: Topic :: Scientific/Engineering :: Chemistry
Classifier: Topic :: Scientific/Engineering :: Artificial Intelligence
Requires-Python: >=3.11
License-File: LICENSE
Requires-Dist: ase>=3.26.0
Requires-Dist: fire>=0.7.1
Requires-Dist: pydantic>=2.12.0
Requires-Dist: pymatgen>=2025.10.7
Requires-Dist: pytorch-lightning>=2.6.0
Requires-Dist: torch>=2.1.0
Requires-Dist: torch-geometric>=2.6.1
Dynamic: license-file
